{
  "dataParameters":{
    "runs_190456_193621":{
      "bins":[
        {
          "efficiency":0.0666666666667,
          "pt":0.0,
          "uncertainty":0.064406118871899995
        },
        {
          "efficiency":0.090909090909100002,
          "pt":20.0,
          "uncertaintyMinus":0.075326880618100001,
          "uncertaintyPlus":0.17929520947399999
        },
        {
          "efficiency":0.0,
          "pt":30.0,
          "uncertaintyMinus":0.0,
          "uncertaintyPlus":0.36887757085
        },
        {
          "efficiency":0.0,
          "pt":40.0,
          "uncertaintyMinus":0.0,
          "uncertaintyPlus":0.84134474606800003
        },
        {
          "efficiency":0.5,
          "pt":50.0,
          "uncertaintyMinus":0.41724846473999999,
          "uncertaintyPlus":0.41724846473999999
        },
        {
          "efficiency":0.0,
          "pt":60.0,
          "uncertaintyMinus":0.0,
          "uncertaintyPlus":1.0
        },
        {
          "efficiency":1.0,
          "pt":70.0,
          "uncertaintyMinus":0.60168447942400005,
          "uncertaintyPlus":0.0
        },
        {
          "efficiency":0.0,
          "pt":80.0,
          "uncertaintyMinus":0.0,
          "uncertaintyPlus":1.0
        },
        {
          "efficiency":0.0,
          "pt":100.0,
          "uncertaintyMinus":0.0,
          "uncertaintyPlus":1.0
        },
        {
          "efficiency":1.0,
          "pt":120.0,
          "uncertaintyMinus":0.84134474606800003,
          "uncertaintyPlus":0.0
        },
        {
          "efficiency":0.0,
          "pt":140.0,
          "uncertaintyMinus":0.0,
          "uncertaintyPlus":1.0
        },
        {
          "efficiency":0.0,
          "pt":160.0,
          "uncertaintyMinus":0.0,
          "uncertaintyPlus":1.0
        }
      ],
      "firstRun":190456,
      "lastRun":193621,
      "luminosity":887.50099999999998
    },
    "runs_190456_196531":{
      "bins":[
        {
          "efficiency":0.032608695652200002,
          "pt":0.0,
          "uncertainty":0.0130935946463
        },
        {
          "efficiency":0.0409836065574,
          "pt":20.0,
          "uncertaintyMinus":0.017589919936700001,
          "uncertaintyPlus":0.026773573917299998
        },
        {
          "efficiency":0.065217391304300001,
          "pt":30.0,
          "uncertaintyMinus":0.025566052289299999,
          "uncertaintyPlus":0.036922659141700002
        },
        {
          "efficiency":0.121951219512,
          "pt":40.0,
          "uncertaintyMinus":0.051645843348500003,
          "uncertaintyPlus":0.074083329851899998
        },
        {
          "efficiency":0.194444444444,
          "pt":50.0,
          "uncertaintyMinus":0.068790877801000003,
          "uncertaintyPlus":0.088942493926799995
        },
        {
          "efficiency":0.40000000000000002,
          "pt":60.0,
          "uncertaintyMinus":0.18000925389399999,
          "uncertaintyPlus":0.20459685423599999
        },
        {
          "efficiency":0.66666666666700003,
          "pt":70.0,
          "uncertaintyMinus":0.414534706285,
          "uncertaintyPlus":0.277375360987
        },
        {
          "efficiency":0.75,
          "pt":80.0,
          "uncertaintyMinus":0.36840242550399999,
          "uncertaintyPlus":0.20773089369600001
        },
        {
          "efficiency":1.0,
          "pt":100.0,
          "uncertaintyMinus":0.84134474606800003,
          "uncertaintyPlus":0.0
        },
        {
          "efficiency":0.5,
          "pt":120.0,
          "uncertaintyMinus":0.31469889387299999,
          "uncertaintyPlus":0.31469889387299999
        },
        {
          "efficiency":0.0,
          "pt":140.0,
          "uncertaintyMinus":0.0,
          "uncertaintyPlus":1.0
        },
        {
          "efficiency":0.0,
          "pt":160.0,
          "uncertaintyMinus":0.0,
          "uncertaintyPlus":1.0
        }
      ],
      "firstRun":190456,
      "lastRun":196531,
      "luminosity":5327.5010000000002
    },
    "runs_190456_203742":{
      "bins":[
        {
          "efficiency":0.029702970297,
          "pt":0.0,
          "uncertainty":0.0084462048206699995
        },
        {
          "efficiency":0.033333333333299998,
          "pt":20.0,
          "uncertaintyMinus":0.010280580498399999,
          "uncertaintyPlus":0.013884163888500001
        },
        {
          "efficiency":0.065656565656599997,
          "pt":30.0,
          "uncertaintyMinus":0.017657486050100001,
          "uncertaintyPlus":0.0226579362019
        },
        {
          "efficiency":0.082568807339400002,
          "pt":40.0,
          "uncertaintyMinus":0.0264930657628,
          "uncertaintyPlus":0.035428805560399998
        },
        {
          "efficiency":0.151515151515,
          "pt":50.0,
          "uncertaintyMinus":0.045333084156999999,
          "uncertaintyPlus":0.057578592879600002
        },
        {
          "efficiency":0.32000000000000001,
          "pt":60.0,
          "uncertaintyMinus":0.102271514956,
          "uncertaintyPlus":0.11927576153900001
        },
        {
          "efficiency":0.5,
          "pt":70.0,
          "uncertaintyMinus":0.176478356266,
          "uncertaintyPlus":0.176478356266
        },
        {
          "efficiency":0.57142857142900005,
          "pt":80.0,
          "uncertaintyMinus":0.24784098827500001,
          "uncertaintyPlus":0.22248761311599999
        },
        {
          "efficiency":1.0,
          "pt":100.0,
          "uncertaintyMinus":0.60168447942400005,
          "uncertaintyPlus":0.0
        },
        {
          "efficiency":0.59999999999999998,
          "pt":120.0,
          "uncertaintyMinus":0.303366136254,
          "uncertaintyPlus":0.25334762524999999
        },
        {
          "efficiency":0.75,
          "pt":140.0,
          "uncertaintyMinus":0.36840242550399999,
          "uncertaintyPlus":0.20773089369600001
        },
        {
          "efficiency":1.0,
          "pt":160.0,
          "uncertaintyMinus":0.60168447942400005,
          "uncertaintyPlus":0.0
        }
      ],
      "firstRun":190456,
      "lastRun":203742,
      "luminosity":12170.501
    },
    "runs_190456_208686":{
      "bins":[
        {
          "efficiency":0.028963414634100001,
          "pt":0.0,
          "uncertainty":0.0065477299229999997
        },
        {
          "efficiency":0.0390143737166,
          "pt":20.0,
          "uncertaintyMinus":0.0087669317070800008,
          "uncertaintyPlus":0.0108791884278
        },
        {
          "efficiency":0.062314540059299997,
          "pt":30.0,
          "uncertaintyMinus":0.0132265720972,
          "uncertaintyPlus":0.016111685627300001
        },
        {
          "efficiency":0.098958333333299994,
          "pt":40.0,
          "uncertaintyMinus":0.021816453264099998,
          "uncertaintyPlus":0.0264833985093
        },
        {
          "efficiency":0.146788990826,
          "pt":50.0,
          "uncertaintyMinus":0.034728130394499998,
          "uncertaintyPlus":0.0420419363152
        },
        {
          "efficiency":0.29545454545499999,
          "pt":60.0,
          "uncertaintyMinus":0.073862941947700003,
          "uncertaintyPlus":0.084530577857200001
        },
        {
          "efficiency":0.38888888888899997,
          "pt":70.0,
          "uncertaintyMinus":0.13064000454300001,
          "uncertaintyPlus":0.14537898576200001
        },
        {
          "efficiency":0.46153846153799999,
          "pt":80.0,
          "uncertaintyMinus":0.16484732239899999,
          "uncertaintyPlus":0.172004084463
        },
        {
          "efficiency":1.0,
          "pt":100.0,
          "uncertaintyMinus":0.60168447942400005,
          "uncertaintyPlus":0.0
        },
        {
          "efficiency":0.75,
          "pt":120.0,
          "uncertaintyMinus":0.23956680273299999,
          "uncertaintyPlus":0.159659347816
        },
        {
          "efficiency":0.75,
          "pt":140.0,
          "uncertaintyMinus":0.36840242550399999,
          "uncertaintyPlus":0.20773089369600001
        },
        {
          "efficiency":1.0,
          "pt":160.0,
          "uncertaintyMinus":0.30802422347699998,
          "uncertaintyPlus":0.0
        }
      ],
      "firstRun":190456,
      "lastRun":208686,
      "luminosity":19769.955000000002
    },
    "runs_193833_196531":{
      "bins":[
        {
          "efficiency":0.029585798816599999,
          "pt":0.0,
          "uncertainty":0.013033974568299999
        },
        {
          "efficiency":0.036036036036000002,
          "pt":20.0,
          "uncertaintyMinus":0.017167775046099999,
          "uncertaintyPlus":0.027576067692900001
        },
        {
          "efficiency":0.068181818181799997,
          "pt":30.0,
          "uncertaintyMinus":0.026713363692199999,
          "uncertaintyPlus":0.038504411867699997
        },
        {
          "efficiency":0.125,
          "pt":40.0,
          "uncertaintyMinus":0.052909213661200001,
          "uncertaintyPlus":0.075719981744800005
        },
        {
          "efficiency":0.176470588235,
          "pt":50.0,
          "uncertaintyMinus":0.067676174904499994,
          "uncertaintyPlus":0.090503907375299994
        },
        {
          "efficiency":0.40000000000000002,
          "pt":60.0,
          "uncertaintyMinus":0.18000925389399999,
          "uncertaintyPlus":0.20459685423599999
        },
        {
          "efficiency":0.0,
          "pt":70.0,
          "uncertaintyMinus":0.0,
          "uncertaintyPlus":0.84134474606800003
        },
        {
          "efficiency":0.75,
          "pt":80.0,
          "uncertaintyMinus":0.36840242550399999,
          "uncertaintyPlus":0.20773089369600001
        },
        {
          "efficiency":1.0,
          "pt":100.0,
          "uncertaintyMinus":0.84134474606800003,
          "uncertaintyPlus":0.0
        },
        {
          "efficiency":0.33333333333300003,
          "pt":120.0,
          "uncertaintyMinus":0.277375360987,
          "uncertaintyPlus":0.414534706285
        },
        {
          "efficiency":0.0,
          "pt":140.0,
          "uncertaintyMinus":0.0,
          "uncertaintyPlus":1.0
        },
        {
          "efficiency":0.0,
          "pt":160.0,
          "uncertaintyMinus":0.0,
          "uncertaintyPlus":1.0
        }
      ],
      "firstRun":193833,
      "lastRun":196531,
      "luminosity":4440.0
    },
    "runs_198022_203742":{
      "bins":[
        {
          "efficiency":0.027272727272700002,
          "pt":0.0,
          "uncertainty":0.010981166857200001
        },
        {
          "efficiency":0.028089887640400001,
          "pt":20.0,
          "uncertaintyMinus":0.012080535501599999,
          "uncertaintyPlus":0.0185555038223
        },
        {
          "efficiency":0.066037735849099999,
          "pt":30.0,
          "uncertaintyMinus":0.024034474071100001,
          "uncertaintyPlus":0.033758047123100002
        },
        {
          "efficiency":0.058823529411800003,
          "pt":40.0,
          "uncertaintyMinus":0.027940846255800001,
          "uncertaintyPlus":0.044070481642600003
        },
        {
          "efficiency":0.10000000000000001,
          "pt":50.0,
          "uncertaintyMinus":0.053922151663400003,
          "uncertaintyPlus":0.087797408454399997
        },
        {
          "efficiency":0.26666666666700001,
          "pt":60.0,
          "uncertaintyMinus":0.122866921165,
          "uncertaintyPlus":0.161145049639
        },
        {
          "efficiency":0.444444444444,
          "pt":70.0,
          "uncertaintyMinus":0.19826714495100001,
          "uncertaintyPlus":0.21346282494800001
        },
        {
          "efficiency":0.33333333333300003,
          "pt":80.0,
          "uncertaintyMinus":0.277375360987,
          "uncertaintyPlus":0.414534706285
        },
        {
          "efficiency":1.0,
          "pt":100.0,
          "uncertaintyMinus":0.84134474606800003,
          "uncertaintyPlus":0.0
        },
        {
          "efficiency":1.0,
          "pt":120.0,
          "uncertaintyMinus":0.84134474606800003,
          "uncertaintyPlus":0.0
        },
        {
          "efficiency":0.75,
          "pt":140.0,
          "uncertaintyMinus":0.36840242550399999,
          "uncertaintyPlus":0.20773089369600001
        },
        {
          "efficiency":1.0,
          "pt":160.0,
          "uncertaintyMinus":0.60168447942400005,
          "uncertaintyPlus":0.0
        }
      ],
      "firstRun":198022,
      "lastRun":203742,
      "luminosity":7124.4539999999997
    },
    "runs_203777_208686":{
      "bins":[
        {
          "efficiency":0.027777777777800002,
          "pt":0.0,
          "uncertainty":0.010352166562499999
        },
        {
          "efficiency":0.048128342246000003,
          "pt":20.0,
          "uncertaintyMinus":0.0155690574289,
          "uncertaintyPlus":0.021206983731399998
        },
        {
          "efficiency":0.0575539568345,
          "pt":30.0,
          "uncertaintyMinus":0.019671711627200002,
          "uncertaintyPlus":0.027159470535999999
        },
        {
          "efficiency":0.120481927711,
          "pt":40.0,
          "uncertaintyMinus":0.036349857182799997,
          "uncertaintyPlus":0.046949480212299999
        },
        {
          "efficiency":0.13953488372100001,
          "pt":50.0,
          "uncertaintyMinus":0.053918316398800001,
          "uncertaintyPlus":0.074035728710200005
        },
        {
          "efficiency":0.26315789473700002,
          "pt":60.0,
          "uncertaintyMinus":0.108565019101,
          "uncertaintyPlus":0.13881997024199999
        },
        {
          "efficiency":0.166666666667,
          "pt":70.0,
          "uncertaintyMinus":0.138284918684,
          "uncertaintyPlus":0.28735038933200002
        },
        {
          "efficiency":0.33333333333300003,
          "pt":80.0,
          "uncertaintyMinus":0.211935221871,
          "uncertaintyPlus":0.28202346208500001
        },
        {
          "efficiency":0.0,
          "pt":100.0,
          "uncertaintyMinus":0.0,
          "uncertaintyPlus":1.0
        },
        {
          "efficiency":1.0,
          "pt":120.0,
          "uncertaintyMinus":0.45864167529599997,
          "uncertaintyPlus":0.0
        },
        {
          "efficiency":0.0,
          "pt":140.0,
          "uncertaintyMinus":0.0,
          "uncertaintyPlus":1.0
        },
        {
          "efficiency":1.0,
          "pt":160.0,
          "uncertaintyMinus":0.45864167529599997,
          "uncertaintyPlus":0.0
        }
      ],
      "firstRun":203777,
      "lastRun":208686,
      "luminosity":7318.0
    }
  },
  "mcParameters":{
    "Summer12_PU_2012A":{
      "bins":[
        {
          "efficiency":0.071266968325799998,
          "pt":0.0,
          "uncertainty":0.0038697103014399999
        },
        {
          "efficiency":0.087272123838399995,
          "pt":20.0,
          "uncertaintyMinus":0.0024288220513900001,
          "uncertaintyPlus":0.0024288220513900001
        },
        {
          "efficiency":0.126994030451,
          "pt":30.0,
          "uncertaintyMinus":0.00310564287951,
          "uncertaintyPlus":0.00310564287951
        },
        {
          "efficiency":0.163781429374,
          "pt":40.0,
          "uncertaintyMinus":0.0038435978885999998,
          "uncertaintyPlus":0.0038435978885999998
        },
        {
          "efficiency":0.212003208379,
          "pt":50.0,
          "uncertaintyMinus":0.0047260375203700003,
          "uncertaintyPlus":0.0047260375203700003
        },
        {
          "efficiency":0.27603453461900002,
          "pt":60.0,
          "uncertaintyMinus":0.00574336809577,
          "uncertaintyPlus":0.00574336809577
        },
        {
          "efficiency":0.32485324950099997,
          "pt":70.0,
          "uncertaintyMinus":0.00644469208608,
          "uncertaintyPlus":0.00644469208608
        },
        {
          "efficiency":0.52092274598900001,
          "pt":80.0,
          "uncertaintyMinus":0.0053870852472099997,
          "uncertaintyPlus":0.0053870852472099997
        },
        {
          "efficiency":0.75717598872299996,
          "pt":100.0,
          "uncertaintyMinus":0.0052053406334300004,
          "uncertaintyPlus":0.0052053406334300004
        },
        {
          "efficiency":0.90893071367900002,
          "pt":120.0,
          "uncertaintyMinus":0.0039389232146899997,
          "uncertaintyPlus":0.0039389232146899997
        },
        {
          "efficiency":0.97918375397199997,
          "pt":140.0,
          "uncertaintyMinus":0.00235900592452,
          "uncertaintyPlus":0.00235900592452
        },
        {
          "efficiency":0.99953910471200003,
          "pt":160.0,
          "uncertaintyMinus":0.00045488586524800002,
          "uncertaintyPlus":0.00045488586524800002
        }
      ]
    },
    "Summer12_PU_2012AB":{
      "bins":[
        {
          "efficiency":0.071266968325799998,
          "pt":0.0,
          "uncertainty":0.0038697103014399999
        },
        {
          "efficiency":0.088802295666200001,
          "pt":20.0,
          "uncertaintyMinus":0.0026273494865300001,
          "uncertaintyPlus":0.0026273494865300001
        },
        {
          "efficiency":0.127173739157,
          "pt":30.0,
          "uncertaintyMinus":0.0033237213068499998,
          "uncertaintyPlus":0.0033237213068499998
        },
        {
          "efficiency":0.16476915757999999,
          "pt":40.0,
          "uncertaintyMinus":0.0041263043455199997,
          "uncertaintyPlus":0.0041263043455199997
        },
        {
          "efficiency":0.226632197052,
          "pt":50.0,
          "uncertaintyMinus":0.0052210774096200004,
          "uncertaintyPlus":0.0052210774096200004
        },
        {
          "efficiency":0.28611084879499998,
          "pt":60.0,
          "uncertaintyMinus":0.0061988971802499999,
          "uncertaintyPlus":0.0061988971802499999
        },
        {
          "efficiency":0.33970985448000002,
          "pt":70.0,
          "uncertaintyMinus":0.0070291565504099996,
          "uncertaintyPlus":0.0070291565504099996
        },
        {
          "efficiency":0.52488808566,
          "pt":80.0,
          "uncertaintyMinus":0.0058696565186499997,
          "uncertaintyPlus":0.0058696565186499997
        },
        {
          "efficiency":0.75886941743199998,
          "pt":100.0,
          "uncertaintyMinus":0.0056566454885999999,
          "uncertaintyPlus":0.0056566454885999999
        },
        {
          "efficiency":0.90850677148299996,
          "pt":120.0,
          "uncertaintyMinus":0.0042530500588099998,
          "uncertaintyPlus":0.0042530500588099998
        },
        {
          "efficiency":0.97480018504900001,
          "pt":140.0,
          "uncertaintyMinus":0.00278207512424,
          "uncertaintyPlus":0.00278207512424
        },
        {
          "efficiency":0.99933768518999999,
          "pt":160.0,
          "uncertaintyMinus":0.00059167636797399998,
          "uncertaintyPlus":0.00059167636797399998
        }
      ]
    },
    "Summer12_PU_2012ABC":{
      "bins":[
        {
          "efficiency":0.071266968325799998,
          "pt":0.0,
          "uncertainty":0.0038697103014399999
        },
        {
          "efficiency":0.088654037178099998,
          "pt":20.0,
          "uncertaintyMinus":0.0026865888693700002,
          "uncertaintyPlus":0.0026865888693700002
        },
        {
          "efficiency":0.12694689767199999,
          "pt":30.0,
          "uncertaintyMinus":0.0033961680412399999,
          "uncertaintyPlus":0.0033961680412399999
        },
        {
          "efficiency":0.16538535719299999,
          "pt":40.0,
          "uncertaintyMinus":0.0042238874081300002,
          "uncertaintyPlus":0.0042238874081300002
        },
        {
          "efficiency":0.22464607211099999,
          "pt":50.0,
          "uncertaintyMinus":0.0053179455892899997,
          "uncertaintyPlus":0.0053179455892899997
        },
        {
          "efficiency":0.28667876239700002,
          "pt":60.0,
          "uncertaintyMinus":0.0063494243066400001,
          "uncertaintyPlus":0.0063494243066400001
        },
        {
          "efficiency":0.33936256414999999,
          "pt":70.0,
          "uncertaintyMinus":0.0071819716653600003,
          "uncertaintyPlus":0.0071819716653600003
        },
        {
          "efficiency":0.52627338614499997,
          "pt":80.0,
          "uncertaintyMinus":0.0059881374149999998,
          "uncertaintyPlus":0.0059881374149999998
        },
        {
          "efficiency":0.75905518622099999,
          "pt":100.0,
          "uncertaintyMinus":0.0057794045811999997,
          "uncertaintyPlus":0.0057794045811999997
        },
        {
          "efficiency":0.90806376670300004,
          "pt":120.0,
          "uncertaintyMinus":0.0043584793542500002,
          "uncertaintyPlus":0.0043584793542500002
        },
        {
          "efficiency":0.97477969284099997,
          "pt":140.0,
          "uncertaintyMinus":0.0028483940864300001,
          "uncertaintyPlus":0.0028483940864300001
        },
        {
          "efficiency":0.99924466419199998,
          "pt":160.0,
          "uncertaintyMinus":0.00064606370031799999,
          "uncertaintyPlus":0.00064606370031799999
        }
      ]
    },
    "Summer12_PU_2012ABCD":{
      "bins":[
        {
          "efficiency":0.071266968325799998,
          "pt":0.0,
          "uncertainty":0.0038697103014399999
        },
        {
          "efficiency":0.089528415813600007,
          "pt":20.0,
          "uncertaintyMinus":0.0030725920564,
          "uncertaintyPlus":0.0030725920564
        },
        {
          "efficiency":0.12667364724899999,
          "pt":30.0,
          "uncertaintyMinus":0.0038552061611,
          "uncertaintyPlus":0.0038552061611
        },
        {
          "efficiency":0.16720098294499999,
          "pt":40.0,
          "uncertaintyMinus":0.0048068440946800002,
          "uncertaintyPlus":0.0048068440946800002
        },
        {
          "efficiency":0.21939834511199999,
          "pt":50.0,
          "uncertaintyMinus":0.0059785846990200002,
          "uncertaintyPlus":0.0059785846990200002
        },
        {
          "efficiency":0.28722719625900001,
          "pt":60.0,
          "uncertaintyMinus":0.0072327650768700003,
          "uncertaintyPlus":0.0072327650768700003
        },
        {
          "efficiency":0.338495693624,
          "pt":70.0,
          "uncertaintyMinus":0.0081498571853099999,
          "uncertaintyPlus":0.0081498571853099999
        },
        {
          "efficiency":0.52966244886000002,
          "pt":80.0,
          "uncertaintyMinus":0.00674471780861,
          "uncertaintyPlus":0.00674471780861
        },
        {
          "efficiency":0.75856276349200003,
          "pt":100.0,
          "uncertaintyMinus":0.0065526592600100003,
          "uncertaintyPlus":0.0065526592600100003
        },
        {
          "efficiency":0.90490866400199998,
          "pt":120.0,
          "uncertaintyMinus":0.0050380058671199998,
          "uncertaintyPlus":0.0050380058671199998
        },
        {
          "efficiency":0.975150994228,
          "pt":140.0,
          "uncertaintyMinus":0.0032284274202900001,
          "uncertaintyPlus":0.0032284274202900001
        },
        {
          "efficiency":0.99892438514399995,
          "pt":160.0,
          "uncertaintyMinus":0.00086566056727800005,
          "uncertaintyPlus":0.00086566056727800005
        }
      ]
    },
    "Summer12_PU_2012B":{
      "bins":[
        {
          "efficiency":0.071266968325799998,
          "pt":0.0,
          "uncertainty":0.0038697103014399999
        },
        {
          "efficiency":0.089086662156699997,
          "pt":20.0,
          "uncertaintyMinus":0.00266319131654,
          "uncertaintyPlus":0.00266319131654
        },
        {
          "efficiency":0.127206789864,
          "pt":30.0,
          "uncertaintyMinus":0.0033624268264799998,
          "uncertaintyPlus":0.0033624268264799998
        },
        {
          "efficiency":0.16495162743700001,
          "pt":40.0,
          "uncertaintyMinus":0.0041767488771799997,
          "uncertaintyPlus":0.0041767488771799997
        },
        {
          "efficiency":0.22938270128800001,
          "pt":50.0,
          "uncertaintyMinus":0.00531205308671,
          "uncertaintyPlus":0.00531205308671
        },
        {
          "efficiency":0.28795998994599997,
          "pt":60.0,
          "uncertaintyMinus":0.00628032901457,
          "uncertaintyPlus":0.00628032901457
        },
        {
          "efficiency":0.34250279871900002,
          "pt":70.0,
          "uncertaintyMinus":0.00713531732437,
          "uncertaintyPlus":0.00713531732437
        },
        {
          "efficiency":0.525653167847,
          "pt":80.0,
          "uncertaintyMinus":0.0059580814598600004,
          "uncertaintyPlus":0.0059580814598600004
        },
        {
          "efficiency":0.75919644945599996,
          "pt":100.0,
          "uncertaintyMinus":0.0057389505571400004,
          "uncertaintyPlus":0.0057389505571400004
        },
        {
          "efficiency":0.90842696782300003,
          "pt":120.0,
          "uncertaintyMinus":0.0043096943541500003,
          "uncertaintyPlus":0.0043096943541500003
        },
        {
          "efficiency":0.97398344910199997,
          "pt":140.0,
          "uncertaintyMinus":0.0028605261398700001,
          "uncertaintyPlus":0.0028605261398700001
        },
        {
          "efficiency":0.99929923706500001,
          "pt":160.0,
          "uncertaintyMinus":0.00061728772759499998,
          "uncertaintyPlus":0.00061728772759499998
        }
      ]
    },
    "Summer12_PU_2012C":{
      "bins":[
        {
          "efficiency":0.071266968325799998,
          "pt":0.0,
          "uncertainty":0.0038697103014399999
        },
        {
          "efficiency":0.088534271484000004,
          "pt":20.0,
          "uncertaintyMinus":0.0027333533498399998,
          "uncertaintyPlus":0.0027333533498399998
        },
        {
          "efficiency":0.12676420917100001,
          "pt":30.0,
          "uncertaintyMinus":0.0034532453211000001,
          "uncertaintyPlus":0.0034532453211000001
        },
        {
          "efficiency":0.16588092087199999,
          "pt":40.0,
          "uncertaintyMinus":0.0043011211388800001,
          "uncertaintyPlus":0.0043011211388800001
        },
        {
          "efficiency":0.223051784108,
          "pt":50.0,
          "uncertaintyMinus":0.0053933878052099997,
          "uncertaintyPlus":0.0053933878052099997
        },
        {
          "efficiency":0.28713837203999998,
          "pt":60.0,
          "uncertaintyMinus":0.0064688082681900001,
          "uncertaintyPlus":0.0064688082681900001
        },
        {
          "efficiency":0.339083711229,
          "pt":70.0,
          "uncertaintyMinus":0.0073023598454600002,
          "uncertaintyPlus":0.0073023598454600002
        },
        {
          "efficiency":0.52738105595700002,
          "pt":80.0,
          "uncertaintyMinus":0.0060810674217600001,
          "uncertaintyPlus":0.0060810674217600001
        },
        {
          "efficiency":0.75920387892899999,
          "pt":100.0,
          "uncertaintyMinus":0.0058761159557500003,
          "uncertaintyPlus":0.0058761159557500003
        },
        {
          "efficiency":0.90770700349,
          "pt":120.0,
          "uncertaintyMinus":0.00444214589454,
          "uncertaintyPlus":0.00444214589454
        },
        {
          "efficiency":0.97476331657199999,
          "pt":140.0,
          "uncertaintyMinus":0.0029009158178900001,
          "uncertaintyPlus":0.0029009158178900001
        },
        {
          "efficiency":0.999169746049,
          "pt":160.0,
          "uncertaintyMinus":0.00068915568027800005,
          "uncertaintyPlus":0.00068915568027800005
        }
      ]
    },
    "Summer12_PU_2012D":{
      "bins":[
        {
          "efficiency":0.071266968325799998,
          "pt":0.0,
          "uncertainty":0.0038697103014399999
        },
        {
          "efficiency":0.089528415813600007,
          "pt":20.0,
          "uncertaintyMinus":0.0030725920564,
          "uncertaintyPlus":0.0030725920564
        },
        {
          "efficiency":0.12667364724899999,
          "pt":30.0,
          "uncertaintyMinus":0.0038552061611,
          "uncertaintyPlus":0.0038552061611
        },
        {
          "efficiency":0.16720098294499999,
          "pt":40.0,
          "uncertaintyMinus":0.0048068440946800002,
          "uncertaintyPlus":0.0048068440946800002
        },
        {
          "efficiency":0.21939834511199999,
          "pt":50.0,
          "uncertaintyMinus":0.0059785846990200002,
          "uncertaintyPlus":0.0059785846990200002
        },
        {
          "efficiency":0.28722719625900001,
          "pt":60.0,
          "uncertaintyMinus":0.0072327650768700003,
          "uncertaintyPlus":0.0072327650768700003
        },
        {
          "efficiency":0.338495693624,
          "pt":70.0,
          "uncertaintyMinus":0.0081498571853099999,
          "uncertaintyPlus":0.0081498571853099999
        },
        {
          "efficiency":0.52966244886000002,
          "pt":80.0,
          "uncertaintyMinus":0.00674471780861,
          "uncertaintyPlus":0.00674471780861
        },
        {
          "efficiency":0.75856276349200003,
          "pt":100.0,
          "uncertaintyMinus":0.0065526592600100003,
          "uncertaintyPlus":0.0065526592600100003
        },
        {
          "efficiency":0.90490866400199998,
          "pt":120.0,
          "uncertaintyMinus":0.0050380058671199998,
          "uncertaintyPlus":0.0050380058671199998
        },
        {
          "efficiency":0.975150994228,
          "pt":140.0,
          "uncertaintyMinus":0.0032284274202900001,
          "uncertaintyPlus":0.0032284274202900001
        },
        {
          "efficiency":0.99892438514399995,
          "pt":160.0,
          "uncertaintyMinus":0.00086566056727800005,
          "uncertaintyPlus":0.00086566056727800005
        }
      ]
    },
    "Summer12_PU_Unweighted":{
      "bins":[
        {
          "efficiency":0.071266968325799998,
          "pt":0.0,
          "uncertainty":0.0038697103014399999
        },
        {
          "efficiency":0.095398138572899999,
          "pt":20.0,
          "uncertaintyMinus":0.0047453501883600001,
          "uncertaintyPlus":0.0049602511487700004
        },
        {
          "efficiency":0.12898508335799999,
          "pt":30.0,
          "uncertaintyMinus":0.0057671319853299999,
          "uncertaintyPlus":0.0059896640169699996
        },
        {
          "efficiency":0.17822838847399999,
          "pt":40.0,
          "uncertaintyMinus":0.0072781417233300002,
          "uncertaintyPlus":0.0075126723944199999
        },
        {
          "efficiency":0.22423146473800001,
          "pt":50.0,
          "uncertaintyMinus":0.0089646235964099992,
          "uncertaintyPlus":0.0092202492990600005
        },
        {
          "efficiency":0.30461367426300001,
          "pt":60.0,
          "uncertaintyMinus":0.011014830624100001,
          "uncertaintyPlus":0.011237535924199999
        },
        {
          "efficiency":0.362433862434,
          "pt":70.0,
          "uncertaintyMinus":0.0125955756572,
          "uncertaintyPlus":0.012782333501800001
        },
        {
          "efficiency":0.54541816726699999,
          "pt":80.0,
          "uncertaintyMinus":0.0101772034537,
          "uncertaintyPlus":0.0101401332957
        },
        {
          "efficiency":0.76000000000000001,
          "pt":100.0,
          "uncertaintyMinus":0.010269975011,
          "uncertaintyPlus":0.0099852340944299994
        },
        {
          "efficiency":0.89169435215899995,
          "pt":120.0,
          "uncertaintyMinus":0.0086137127568099991,
          "uncertaintyPlus":0.0080718002294400005
        },
        {
          "efficiency":0.96605237633399998,
          "pt":140.0,
          "uncertaintyMinus":0.0066243460833900003,
          "uncertaintyPlus":0.0056429673972499999
        },
        {
          "efficiency":0.99708029197100001,
          "pt":160.0,
          "uncertaintyMinus":0.0038378631591900001,
          "uncertaintyPlus":0.0018856401633199999
        }
      ]
    }
  }
}