{
  "dataParameters":{
    "runs_190456_193621":{
      "bins":[
        {
          "efficiency":0.029850746268700001,
          "pt":20.0,
          "uncertaintyMinus":0.00393205368448,
          "uncertaintyPlus":0.00446717238774
        },
        {
          "efficiency":0.033923303834800002,
          "pt":25.0,
          "uncertaintyMinus":0.0049213603109899999,
          "uncertaintyPlus":0.0056601143956899998
        },
        {
          "efficiency":0.070640176600400006,
          "pt":29.0,
          "uncertaintyMinus":0.0069876893790999997,
          "uncertaintyPlus":0.0076527601811900003
        },
        {
          "efficiency":0.47992863514700002,
          "pt":33.0,
          "uncertaintyMinus":0.0153422064419,
          "uncertaintyPlus":0.015379066325199999
        },
        {
          "efficiency":0.76545842217500004,
          "pt":37.0,
          "uncertaintyMinus":0.014655430099299999,
          "uncertaintyPlus":0.014067990510299999
        },
        {
          "efficiency":0.784496124031,
          "pt":41.0,
          "uncertaintyMinus":0.017417038139500001,
          "uncertaintyPlus":0.016493509086400002
        },
        {
          "efficiency":0.76572668112800002,
          "pt":45.0,
          "uncertaintyMinus":0.021400094021600001,
          "uncertaintyPlus":0.020185501854100001
        },
        {
          "efficiency":0.79537953795399996,
          "pt":50.0,
          "uncertaintyMinus":0.025838135875400001,
          "uncertaintyPlus":0.023753885732100001
        },
        {
          "efficiency":0.76851851851899999,
          "pt":55.0,
          "uncertaintyMinus":0.0322931150275,
          "uncertaintyPlus":0.029614119839900001
        },
        {
          "efficiency":0.77777777777799995,
          "pt":60.0,
          "uncertaintyMinus":0.030541178153799999,
          "uncertaintyPlus":0.027987211503999999
        },
        {
          "efficiency":0.68067226890800003,
          "pt":70.0,
          "uncertaintyMinus":0.048400115276200001,
          "uncertaintyPlus":0.045083167596599999
        },
        {
          "efficiency":0.70588235294099999,
          "pt":80.0,
          "uncertaintyMinus":0.044244130757899999,
          "uncertaintyPlus":0.040947195616599999
        },
        {
          "efficiency":0.70129870129899996,
          "pt":100.0,
          "uncertaintyMinus":0.061183728180000001,
          "uncertaintyPlus":0.055354417061
        }
      ],
      "firstRun":190456,
      "lastRun":193621,
      "luminosity":697.30799999999999
    },
    "runs_190456_196531":{
      "bins":[
        {
          "efficiency":0.0311313591496,
          "pt":20.0,
          "uncertaintyMinus":0.00159704518223,
          "uncertaintyPlus":0.00167824941692
        },
        {
          "efficiency":0.0373967403438,
          "pt":25.0,
          "uncertaintyMinus":0.0020076971429700001,
          "uncertaintyPlus":0.0021138517350600002
        },
        {
          "efficiency":0.091729866377800007,
          "pt":29.0,
          "uncertaintyMinus":0.0031771146055800002,
          "uncertaintyPlus":0.0032772721198799999
        },
        {
          "efficiency":0.48045310125700003,
          "pt":33.0,
          "uncertaintyMinus":0.0059380934162199996,
          "uncertaintyPlus":0.0059435569218900001
        },
        {
          "efficiency":0.77823298895600002,
          "pt":37.0,
          "uncertaintyMinus":0.0056836122840700004,
          "uncertaintyPlus":0.0055829094630599997
        },
        {
          "efficiency":0.79471996052299998,
          "pt":41.0,
          "uncertaintyMinus":0.0065413723508500003,
          "uncertaintyPlus":0.0063931327917800002
        },
        {
          "efficiency":0.79771888627999998,
          "pt":45.0,
          "uncertaintyMinus":0.0076263720730299998,
          "uncertaintyPlus":0.0074221141896699998
        },
        {
          "efficiency":0.81182212581299995,
          "pt":50.0,
          "uncertaintyMinus":0.0095456081978200005,
          "uncertaintyPlus":0.0091974418511300005
        },
        {
          "efficiency":0.80871670702200005,
          "pt":55.0,
          "uncertaintyMinus":0.0118324067484,
          "uncertaintyPlus":0.0113163235794
        },
        {
          "efficiency":0.76986301369900001,
          "pt":60.0,
          "uncertaintyMinus":0.0115459837808,
          "uncertaintyPlus":0.011164971932100001
        },
        {
          "efficiency":0.73832923832899999,
          "pt":70.0,
          "uncertaintyMinus":0.016316126662999999,
          "uncertaintyPlus":0.015707659026099999
        },
        {
          "efficiency":0.75722543352600002,
          "pt":80.0,
          "uncertaintyMinus":0.017399381664299999,
          "uncertaintyPlus":0.016623681879599998
        },
        {
          "efficiency":0.743820224719,
          "pt":100.0,
          "uncertaintyMinus":0.022372592790199999,
          "uncertaintyPlus":0.0212188718405
        }
      ],
      "firstRun":190456,
      "lastRun":196531,
      "luminosity":5126
    },
    "runs_190456_202585":{
      "bins":[
        {
          "efficiency":0.0302141764406,
          "pt":20.0,
          "uncertaintyMinus":0.00136805792179,
          "uncertaintyPlus":0.0014293448177600001
        },
        {
          "efficiency":0.0369472540333,
          "pt":25.0,
          "uncertaintyMinus":0.0017269957147400001,
          "uncertaintyPlus":0.0018062838865399999
        },
        {
          "efficiency":0.090958506975899994,
          "pt":29.0,
          "uncertaintyMinus":0.0027446271325599998,
          "uncertaintyPlus":0.0028199654936599998
        },
        {
          "efficiency":0.45965132059699998,
          "pt":33.0,
          "uncertaintyMinus":0.0051397053948600002,
          "uncertaintyPlus":0.0051482156172999996
        },
        {
          "efficiency":0.73928762720899999,
          "pt":37.0,
          "uncertaintyMinus":0.0051793854911499999,
          "uncertaintyPlus":0.0051144626233900004
        },
        {
          "efficiency":0.76018779342700005,
          "pt":41.0,
          "uncertaintyMinus":0.0059941890464399999,
          "uncertaintyPlus":0.0058949086825999999
        },
        {
          "efficiency":0.76249689132099996,
          "pt":45.0,
          "uncertaintyMinus":0.0069011653808400001,
          "uncertaintyPlus":0.0067682027319800001
        },
        {
          "efficiency":0.76234443998400003,
          "pt":50.0,
          "uncertaintyMinus":0.0088354380896099993,
          "uncertaintyPlus":0.0086198981704899997
        },
        {
          "efficiency":0.77324535093000002,
          "pt":55.0,
          "uncertaintyMinus":0.010721988496700001,
          "uncertaintyPlus":0.010384692532000001
        },
        {
          "efficiency":0.74183514774500003,
          "pt":60.0,
          "uncertaintyMinus":0.0103496538986,
          "uncertaintyPlus":0.0100924749614
        },
        {
          "efficiency":0.72701949860699999,
          "pt":70.0,
          "uncertaintyMinus":0.014251202354899999,
          "uncertaintyPlus":0.0138154525404
        },
        {
          "efficiency":0.70689655172400001,
          "pt":80.0,
          "uncertaintyMinus":0.0157042937376,
          "uncertaintyPlus":0.0152426213441
        },
        {
          "efficiency":0.70868824531499996,
          "pt":100.0,
          "uncertaintyMinus":0.0199615843095,
          "uncertaintyPlus":0.019219035577299998
        }
      ],
      "firstRun":190456,
      "lastRun":202585,
      "luminosity":11736
    },
    "runs_190456_208686":{
      "bins":[
        {
          "efficiency":0.029009835445399999,
          "pt":20.0,
          "uncertaintyMinus":0.00081664093833600003,
          "uncertaintyPlus":0.000839234597406
        },
        {
          "efficiency":0.040444485830499997,
          "pt":25.0,
          "uncertaintyMinus":0.0010986426408,
          "uncertaintyPlus":0.00112757452565
        },
        {
          "efficiency":0.099625317810800001,
          "pt":29.0,
          "uncertaintyMinus":0.00173549238352,
          "uncertaintyPlus":0.00176253867307
        },
        {
          "efficiency":0.47368218397400003,
          "pt":33.0,
          "uncertaintyMinus":0.00311647060627,
          "uncertaintyPlus":0.0031185098604000002
        },
        {
          "efficiency":0.76109769916699999,
          "pt":37.0,
          "uncertaintyMinus":0.0030306002795600002,
          "uncertaintyPlus":0.00300466156128
        },
        {
          "efficiency":0.79603496936700002,
          "pt":41.0,
          "uncertaintyMinus":0.0033980806315500002,
          "uncertaintyPlus":0.0033569061462399999
        },
        {
          "efficiency":0.78558443919300003,
          "pt":45.0,
          "uncertaintyMinus":0.0039843893650500003,
          "uncertaintyPlus":0.0039318741498099996
        },
        {
          "efficiency":0.79118086696599998,
          "pt":50.0,
          "uncertaintyMinus":0.0050881272070800003,
          "uncertaintyPlus":0.0049997761098999997
        },
        {
          "efficiency":0.77597475771900004,
          "pt":55.0,
          "uncertaintyMinus":0.0064347995134400003,
          "uncertaintyPlus":0.00630817970239
        },
        {
          "efficiency":0.76689189189200002,
          "pt":60.0,
          "uncertaintyMinus":0.0059367932912800002,
          "uncertaintyPlus":0.00583499678831
        },
        {
          "efficiency":0.768461007591,
          "pt":70.0,
          "uncertaintyMinus":0.0081017705579199996,
          "uncertaintyPlus":0.0079124563810599995
        },
        {
          "efficiency":0.75741568468099996,
          "pt":80.0,
          "uncertaintyMinus":0.0089493601302899992,
          "uncertaintyPlus":0.0087352969679999996
        },
        {
          "efficiency":0.75247524752499995,
          "pt":100.0,
          "uncertaintyMinus":0.0115864253646,
          "uncertaintyPlus":0.011243339871300001
        }
      ],
      "firstRun":190456,
      "lastRun":208686,
      "luminosity":19296
    },
    "runs_193834_196531":{
      "bins":[
        {
          "efficiency":0.0313721559587,
          "pt":20.0,
          "uncertaintyMinus":0.0017473472956399999,
          "uncertaintyPlus":0.0018439839414100001
        },
        {
          "efficiency":0.038016311497000001,
          "pt":25.0,
          "uncertaintyMinus":0.0021969235192700002,
          "uncertaintyPlus":0.00232210536209
        },
        {
          "efficiency":0.095854922279799998,
          "pt":29.0,
          "uncertaintyMinus":0.0035444719177399999,
          "uncertaintyPlus":0.0036631677454200002
        },
        {
          "efficiency":0.48054919908499999,
          "pt":33.0,
          "uncertaintyMinus":0.0064655522569399999,
          "uncertaintyPlus":0.0064719915214100001
        },
        {
          "efficiency":0.78079555175399995,
          "pt":37.0,
          "uncertaintyMinus":0.0062175717579899996,
          "uncertaintyPlus":0.0060953636344499998
        },
        {
          "efficiency":0.79665492957700001,
          "pt":41.0,
          "uncertaintyMinus":0.0071293986900199998,
          "uncertaintyPlus":0.0069516312158300004
        },
        {
          "efficiency":0.80357142857099995,
          "pt":45.0,
          "uncertaintyMinus":0.0082351625050400001,
          "uncertaintyPlus":0.0079882499992100005
        },
        {
          "efficiency":0.81505515898799996,
          "pt":50.0,
          "uncertaintyMinus":0.0104239112815,
          "uncertaintyPlus":0.010001760873000001
        },
        {
          "efficiency":0.81720430107499997,
          "pt":55.0,
          "uncertaintyMinus":0.0128914341666,
          "uncertaintyPlus":0.012246579657900001
        },
        {
          "efficiency":0.76835236541600005,
          "pt":60.0,
          "uncertaintyMinus":0.0126790277516,
          "uncertaintyPlus":0.0122266626695
        },
        {
          "efficiency":0.74820143884900003,
          "pt":70.0,
          "uncertaintyMinus":0.0175458154781,
          "uncertaintyPlus":0.016801010737000001
        },
        {
          "efficiency":0.76978417266200005,
          "pt":80.0,
          "uncertaintyMinus":0.019248208388799998,
          "uncertaintyPlus":0.018229998410999999
        },
        {
          "efficiency":0.75271739130399995,
          "pt":100.0,
          "uncertaintyMinus":0.024548291381600001,
          "uncertaintyPlus":0.023094302608500001
        }
      ],
      "firstRun":193834,
      "lastRun":196531,
      "luminosity":4428
    },
    "runs_198022_203742":{
      "bins":[
        {
          "efficiency":0.032073011733999998,
          "pt":20.0,
          "uncertaintyMinus":0.00284928842685,
          "uncertaintyPlus":0.0031044787342599999
        },
        {
          "efficiency":0.042928452579,
          "pt":25.0,
          "uncertaintyMinus":0.0037064936635200002,
          "uncertaintyPlus":0.0040243466916599999
        },
        {
          "efficiency":0.105822043208,
          "pt":29.0,
          "uncertaintyMinus":0.0059205777754300004,
          "uncertaintyPlus":0.0062181669343599998
        },
        {
          "efficiency":0.488034188034,
          "pt":33.0,
          "uncertaintyMinus":0.0105394259213,
          "uncertaintyPlus":0.010549861865400001
        },
        {
          "efficiency":0.78748651564200001,
          "pt":37.0,
          "uncertaintyMinus":0.0099280290408699998,
          "uncertaintyPlus":0.0096092019860399992
        },
        {
          "efficiency":0.83411949685499998,
          "pt":41.0,
          "uncertaintyMinus":0.011092930747200001,
          "uncertaintyPlus":0.0105480363074
        },
        {
          "efficiency":0.79807692307699996,
          "pt":45.0,
          "uncertaintyMinus":0.013221996524200001,
          "uncertaintyPlus":0.012626973839099999
        },
        {
          "efficiency":0.79443585780500003,
          "pt":50.0,
          "uncertaintyMinus":0.017127735345299998,
          "uncertaintyPlus":0.0161741975064
        },
        {
          "efficiency":0.85280373831800005,
          "pt":55.0,
          "uncertaintyMinus":0.019163656210100001,
          "uncertaintyPlus":0.017405060008399999
        },
        {
          "efficiency":0.80597014925400001,
          "pt":60.0,
          "uncertaintyMinus":0.020001897371900001,
          "uncertaintyPlus":0.018622735292800001
        },
        {
          "efficiency":0.83269961977200002,
          "pt":70.0,
          "uncertaintyMinus":0.026254367390100002,
          "uncertaintyPlus":0.023521796675100001
        },
        {
          "efficiency":0.78389830508500002,
          "pt":80.0,
          "uncertaintyMinus":0.030157012692199999,
          "uncertaintyPlus":0.0275677321872
        },
        {
          "efficiency":0.72535211267599997,
          "pt":100.0,
          "uncertaintyMinus":0.042569997530299997,
          "uncertaintyPlus":0.039113319134399999
        }
      ],
      "firstRun":198022,
      "lastRun":203742,
      "luminosity":6892
    },
    "runs_202807_208686":{
      "bins":[
        {
          "efficiency":0.027172551965899999,
          "pt":20.0,
          "uncertaintyMinus":0.0012876471860599999,
          "uncertaintyPlus":0.0013482942254400001
        },
        {
          "efficiency":0.046453753629199998,
          "pt":25.0,
          "uncertaintyMinus":0.0019200957775000001,
          "uncertaintyPlus":0.0019969676765199998
        },
        {
          "efficiency":0.104808548531,
          "pt":29.0,
          "uncertaintyMinus":0.0028992590796900002,
          "uncertaintyPlus":0.0029707212821799998
        },
        {
          "efficiency":0.48497898082599999,
          "pt":33.0,
          "uncertaintyMinus":0.00511007884129,
          "uncertaintyPlus":0.0051131901396199997
        },
        {
          "efficiency":0.77073107724099998,
          "pt":37.0,
          "uncertaintyMinus":0.0048772546138200002,
          "uncertaintyPlus":0.00480637625168
        },
        {
          "efficiency":0.82233223322299998,
          "pt":41.0,
          "uncertaintyMinus":0.0053272656194900004,
          "uncertaintyPlus":0.0052069842979100001
        },
        {
          "efficiency":0.81084280303,
          "pt":45.0,
          "uncertaintyMinus":0.0062187971037599996,
          "uncertaintyPlus":0.0060687471136000003
        },
        {
          "efficiency":0.81952191235100003,
          "pt":50.0,
          "uncertaintyMinus":0.0080052355422799999,
          "uncertaintyPlus":0.00774408990032
        },
        {
          "efficiency":0.78163017031600002,
          "pt":55.0,
          "uncertaintyMinus":0.010667506890200001,
          "uncertaintyPlus":0.0103147920701
        },
        {
          "efficiency":0.80110220440900004,
          "pt":60.0,
          "uncertaintyMinus":0.0093386940345199995,
          "uncertaintyPlus":0.0090286208556900008
        },
        {
          "efficiency":0.80036133694699996,
          "pt":70.0,
          "uncertaintyMinus":0.0127433569152,
          "uncertaintyPlus":0.0121806000753
        },
        {
          "efficiency":0.80726872246699999,
          "pt":80.0,
          "uncertaintyMinus":0.013988229045,
          "uncertaintyPlus":0.0132834178979
        },
        {
          "efficiency":0.820754716981,
          "pt":100.0,
          "uncertaintyMinus":0.018232569140300001,
          "uncertaintyPlus":0.016955092901100002
        }
      ],
      "firstRun":202807,
      "lastRun":208686,
      "luminosity":7274
    }
  },
  "mcParameters":{
    "Summer12_PU_2012A":{
      "bins":[
        {
          "efficiency":0.054749590730700001,
          "pt":20.0,
          "uncertaintyMinus":0.00075818477096099997,
          "uncertaintyPlus":0.00075818477096099997
        },
        {
          "efficiency":0.048895890025700002,
          "pt":25.0,
          "uncertaintyMinus":0.000795242383963,
          "uncertaintyPlus":0.000795242383963
        },
        {
          "efficiency":0.0934308395565,
          "pt":29.0,
          "uncertaintyMinus":0.00106847504292,
          "uncertaintyPlus":0.00106847504292
        },
        {
          "efficiency":0.53574284188099996,
          "pt":33.0,
          "uncertaintyMinus":0.00190764501628,
          "uncertaintyPlus":0.00190764501628
        },
        {
          "efficiency":0.82958615001000002,
          "pt":37.0,
          "uncertaintyMinus":0.0016060144295800001,
          "uncertaintyPlus":0.0016060144295800001
        },
        {
          "efficiency":0.84577090076799999,
          "pt":41.0,
          "uncertaintyMinus":0.0018062080443499999,
          "uncertaintyPlus":0.0018062080443499999
        },
        {
          "efficiency":0.83437280875300002,
          "pt":45.0,
          "uncertaintyMinus":0.0019729428176800002,
          "uncertaintyPlus":0.0019729428176800002
        },
        {
          "efficiency":0.83747522970099997,
          "pt":50.0,
          "uncertaintyMinus":0.0023066015232999998,
          "uncertaintyPlus":0.0023066015232999998
        },
        {
          "efficiency":0.82998057414399995,
          "pt":55.0,
          "uncertaintyMinus":0.0028160069448000002,
          "uncertaintyPlus":0.0028160069448000002
        },
        {
          "efficiency":0.845775509014,
          "pt":60.0,
          "uncertaintyMinus":0.0023670791000300001,
          "uncertaintyPlus":0.0023670791000300001
        },
        {
          "efficiency":0.84752518890100004,
          "pt":70.0,
          "uncertaintyMinus":0.0029674368247700001,
          "uncertaintyPlus":0.0029674368247700001
        },
        {
          "efficiency":0.82822724447700002,
          "pt":80.0,
          "uncertaintyMinus":0.00307924580378,
          "uncertaintyPlus":0.00307924580378
        },
        {
          "efficiency":0.78575124816399999,
          "pt":100.0,
          "uncertaintyMinus":0.0040539290582800001,
          "uncertaintyPlus":0.0040539290582800001
        }
      ]
    },
    "Summer12_PU_2012AB":{
      "bins":[
        {
          "efficiency":0.051425462607600003,
          "pt":20.0,
          "uncertaintyMinus":0.00079543797253199999,
          "uncertaintyPlus":0.00079543797253199999
        },
        {
          "efficiency":0.048319242581800002,
          "pt":25.0,
          "uncertaintyMinus":0.00085089706574000001,
          "uncertaintyPlus":0.00085089706574000001
        },
        {
          "efficiency":0.092432026749000001,
          "pt":29.0,
          "uncertaintyMinus":0.00114553112983,
          "uncertaintyPlus":0.00114553112983
        },
        {
          "efficiency":0.53248347958599995,
          "pt":33.0,
          "uncertaintyMinus":0.0020615029533499999,
          "uncertaintyPlus":0.0020615029533499999
        },
        {
          "efficiency":0.82773740745000002,
          "pt":37.0,
          "uncertaintyMinus":0.00173264108202,
          "uncertaintyPlus":0.00173264108202
        },
        {
          "efficiency":0.84692043922799998,
          "pt":41.0,
          "uncertaintyMinus":0.0019348492054500001,
          "uncertaintyPlus":0.0019348492054500001
        },
        {
          "efficiency":0.83593642260800005,
          "pt":45.0,
          "uncertaintyMinus":0.00210279695989,
          "uncertaintyPlus":0.00210279695989
        },
        {
          "efficiency":0.84182565481000005,
          "pt":50.0,
          "uncertaintyMinus":0.00247502848544,
          "uncertaintyPlus":0.00247502848544
        },
        {
          "efficiency":0.827936288435,
          "pt":55.0,
          "uncertaintyMinus":0.00303917561986,
          "uncertaintyPlus":0.00303917561986
        },
        {
          "efficiency":0.84452147093399998,
          "pt":60.0,
          "uncertaintyMinus":0.0025415510662899999,
          "uncertaintyPlus":0.0025415510662899999
        },
        {
          "efficiency":0.85166313944799998,
          "pt":70.0,
          "uncertaintyMinus":0.0031646429595999998,
          "uncertaintyPlus":0.0031646429595999998
        },
        {
          "efficiency":0.82099516871599998,
          "pt":80.0,
          "uncertaintyMinus":0.0033604037515600001,
          "uncertaintyPlus":0.0033604037515600001
        },
        {
          "efficiency":0.79210028606799998,
          "pt":100.0,
          "uncertaintyMinus":0.0043401544974100001,
          "uncertaintyPlus":0.0043401544974100001
        }
      ]
    },
    "Summer12_PU_2012ABC":{
      "bins":[
        {
          "efficiency":0.051858472373499997,
          "pt":20.0,
          "uncertaintyMinus":0.000816555408367,
          "uncertaintyPlus":0.000816555408367
        },
        {
          "efficiency":0.0485816476266,
          "pt":25.0,
          "uncertaintyMinus":0.00087301424664300005,
          "uncertaintyPlus":0.00087301424664300005
        },
        {
          "efficiency":0.093674479624300006,
          "pt":29.0,
          "uncertaintyMinus":0.0011798447905899999,
          "uncertaintyPlus":0.0011798447905899999
        },
        {
          "efficiency":0.53356694362699997,
          "pt":33.0,
          "uncertaintyMinus":0.0021098849589299999,
          "uncertaintyPlus":0.0021098849589299999
        },
        {
          "efficiency":0.82756731315999998,
          "pt":37.0,
          "uncertaintyMinus":0.0017748673164,
          "uncertaintyPlus":0.0017748673164
        },
        {
          "efficiency":0.84682988592700004,
          "pt":41.0,
          "uncertaintyMinus":0.00198205292821,
          "uncertaintyPlus":0.00198205292821
        },
        {
          "efficiency":0.83591556705799996,
          "pt":45.0,
          "uncertaintyMinus":0.0021551103093700001,
          "uncertaintyPlus":0.0021551103093700001
        },
        {
          "efficiency":0.84049137408600005,
          "pt":50.0,
          "uncertaintyMinus":0.0025398155426599998,
          "uncertaintyPlus":0.0025398155426599998
        },
        {
          "efficiency":0.82751645089100001,
          "pt":55.0,
          "uncertaintyMinus":0.0031133699734300002,
          "uncertaintyPlus":0.0031133699734300002
        },
        {
          "efficiency":0.84416779551499999,
          "pt":60.0,
          "uncertaintyMinus":0.0026035380457299999,
          "uncertaintyPlus":0.0026035380457299999
        },
        {
          "efficiency":0.85036540826600004,
          "pt":70.0,
          "uncertaintyMinus":0.00324709642575,
          "uncertaintyPlus":0.00324709642575
        },
        {
          "efficiency":0.82174891185700005,
          "pt":80.0,
          "uncertaintyMinus":0.0034370315306899999,
          "uncertaintyPlus":0.0034370315306899999
        },
        {
          "efficiency":0.79231541559899998,
          "pt":100.0,
          "uncertaintyMinus":0.0044386753010200002,
          "uncertaintyPlus":0.0044386753010200002
        }
      ]
    },
    "Summer12_PU_2012ABCD":{
      "bins":[
        {
          "efficiency":0.053909473780499997,
          "pt":20.0,
          "uncertaintyMinus":0.00094591973542099996,
          "uncertaintyPlus":0.00094591973542099996
        },
        {
          "efficiency":0.049597937143600002,
          "pt":25.0,
          "uncertaintyMinus":0.00100318382647,
          "uncertaintyPlus":0.00100318382647
        },
        {
          "efficiency":0.099059228614599995,
          "pt":29.0,
          "uncertaintyMinus":0.0013798894977699999,
          "uncertaintyPlus":0.0013798894977699999
        },
        {
          "efficiency":0.53914711975499996,
          "pt":33.0,
          "uncertaintyMinus":0.0024055405802699999,
          "uncertaintyPlus":0.0024055405802699999
        },
        {
          "efficiency":0.82620762624499999,
          "pt":37.0,
          "uncertaintyMinus":0.0020378878890699999,
          "uncertaintyPlus":0.0020378878890699999
        },
        {
          "efficiency":0.84307942048700002,
          "pt":41.0,
          "uncertaintyMinus":0.0022864956097400002,
          "uncertaintyPlus":0.0022864956097400002
        },
        {
          "efficiency":0.83543106593700001,
          "pt":45.0,
          "uncertaintyMinus":0.0024743837258399998,
          "uncertaintyPlus":0.0024743837258399998
        },
        {
          "efficiency":0.83505321951699996,
          "pt":50.0,
          "uncertaintyMinus":0.00292746885214,
          "uncertaintyPlus":0.00292746885214
        },
        {
          "efficiency":0.82430701343299995,
          "pt":55.0,
          "uncertaintyMinus":0.0035715454239800002,
          "uncertaintyPlus":0.0035715454239800002
        },
        {
          "efficiency":0.84137920696599999,
          "pt":60.0,
          "uncertaintyMinus":0.0029779644464299998,
          "uncertaintyPlus":0.0029779644464299998
        },
        {
          "efficiency":0.84696894892899999,
          "pt":70.0,
          "uncertaintyMinus":0.0037322820590000002,
          "uncertaintyPlus":0.0037322820590000002
        },
        {
          "efficiency":0.82036472403500005,
          "pt":80.0,
          "uncertaintyMinus":0.0039367618839299999,
          "uncertaintyPlus":0.0039367618839299999
        },
        {
          "efficiency":0.79054373440400005,
          "pt":100.0,
          "uncertaintyMinus":0.0050594940134699997,
          "uncertaintyPlus":0.0050594940134699997
        }
      ]
    },
    "Summer12_PU_2012B":{
      "bins":[
        {
          "efficiency":0.050797806084499998,
          "pt":20.0,
          "uncertaintyMinus":0.00080148691350000005,
          "uncertaintyPlus":0.00080148691350000005
        },
        {
          "efficiency":0.048211551559800003,
          "pt":25.0,
          "uncertaintyMinus":0.000860761286916,
          "uncertaintyPlus":0.000860761286916
        },
        {
          "efficiency":0.092244988616199994,
          "pt":29.0,
          "uncertaintyMinus":0.00115924129371,
          "uncertaintyPlus":0.00115924129371
        },
        {
          "efficiency":0.53186805269899995,
          "pt":33.0,
          "uncertaintyMinus":0.0020892840217200002,
          "uncertaintyPlus":0.0020892840217200002
        },
        {
          "efficiency":0.82739310762899998,
          "pt":37.0,
          "uncertaintyMinus":0.00175542726266,
          "uncertaintyPlus":0.00175542726266
        },
        {
          "efficiency":0.84713406944699998,
          "pt":41.0,
          "uncertaintyMinus":0.00195771476294,
          "uncertaintyPlus":0.00195771476294
        },
        {
          "efficiency":0.83622486715699995,
          "pt":45.0,
          "uncertaintyMinus":0.00212565943029,
          "uncertaintyPlus":0.00212565943029
        },
        {
          "efficiency":0.84265507396799999,
          "pt":50.0,
          "uncertaintyMinus":0.0025048868683400002,
          "uncertaintyPlus":0.0025048868683400002
        },
        {
          "efficiency":0.82755531970499996,
          "pt":55.0,
          "uncertaintyMinus":0.0030793499057399998,
          "uncertaintyPlus":0.0030793499057399998
        },
        {
          "efficiency":0.84428959348099997,
          "pt":60.0,
          "uncertaintyMinus":0.0025726864226999998,
          "uncertaintyPlus":0.0025726864226999998
        },
        {
          "efficiency":0.85244130578300004,
          "pt":70.0,
          "uncertaintyMinus":0.0031991953440400002,
          "uncertaintyPlus":0.0031991953440400002
        },
        {
          "efficiency":0.81965033004099996,
          "pt":80.0,
          "uncertaintyMinus":0.0034115625261499998,
          "uncertaintyPlus":0.0034115625261499998
        },
        {
          "efficiency":0.79330431759599995,
          "pt":100.0,
          "uncertaintyMinus":0.0043906302911600002,
          "uncertaintyPlus":0.0043906302911600002
        }
      ]
    },
    "Summer12_PU_2012C":{
      "bins":[
        {
          "efficiency":0.052207271880200003,
          "pt":20.0,
          "uncertaintyMinus":0.00083336855699600002,
          "uncertaintyPlus":0.00083336855699600002
        },
        {
          "efficiency":0.048793720056299998,
          "pt":25.0,
          "uncertaintyMinus":0.00089062111180500001,
          "uncertaintyPlus":0.00089062111180500001
        },
        {
          "efficiency":0.094679861237999999,
          "pt":29.0,
          "uncertaintyMinus":0.0012073366447399999,
          "uncertaintyPlus":0.0012073366447399999
        },
        {
          "efficiency":0.53444410901200001,
          "pt":33.0,
          "uncertaintyMinus":0.0021481737872800001,
          "uncertaintyPlus":0.0021481737872800001
        },
        {
          "efficiency":0.82742905983799997,
          "pt":37.0,
          "uncertaintyMinus":0.0018083712620100001,
          "uncertaintyPlus":0.0018083712620100001
        },
        {
          "efficiency":0.846758079311,
          "pt":41.0,
          "uncertaintyMinus":0.00201949911054,
          "uncertaintyPlus":0.00201949911054
        },
        {
          "efficiency":0.83589900274200002,
          "pt":45.0,
          "uncertaintyMinus":0.0021966665586999998,
          "uncertaintyPlus":0.0021966665586999998
        },
        {
          "efficiency":0.83941629134100004,
          "pt":50.0,
          "uncertaintyMinus":0.0025913483866799999,
          "uncertaintyPlus":0.0025913483866799999
        },
        {
          "efficiency":0.827177211962,
          "pt":55.0,
          "uncertaintyMinus":0.0031722249410900002,
          "uncertaintyPlus":0.0031722249410900002
        },
        {
          "efficiency":0.843882977669,
          "pt":60.0,
          "uncertaintyMinus":0.0026527054914000001,
          "uncertaintyPlus":0.0026527054914000001
        },
        {
          "efficiency":0.84932100476399996,
          "pt":70.0,
          "uncertaintyMinus":0.0033126496652599998,
          "uncertaintyPlus":0.0033126496652599998
        },
        {
          "efficiency":0.82235952964000003,
          "pt":80.0,
          "uncertaintyMinus":0.0034975343894200002,
          "uncertaintyPlus":0.0034975343894200002
        },
        {
          "efficiency":0.79248890304499997,
          "pt":100.0,
          "uncertaintyMinus":0.0045164866879900002,
          "uncertaintyPlus":0.0045164866879900002
        }
      ]
    },
    "Summer12_PU_2012D":{
      "bins":[
        {
          "efficiency":0.053909473780499997,
          "pt":20.0,
          "uncertaintyMinus":0.00094591973542099996,
          "uncertaintyPlus":0.00094591973542099996
        },
        {
          "efficiency":0.049597937143600002,
          "pt":25.0,
          "uncertaintyMinus":0.00100318382647,
          "uncertaintyPlus":0.00100318382647
        },
        {
          "efficiency":0.099059228614599995,
          "pt":29.0,
          "uncertaintyMinus":0.0013798894977699999,
          "uncertaintyPlus":0.0013798894977699999
        },
        {
          "efficiency":0.53914711975499996,
          "pt":33.0,
          "uncertaintyMinus":0.0024055405802699999,
          "uncertaintyPlus":0.0024055405802699999
        },
        {
          "efficiency":0.82620762624499999,
          "pt":37.0,
          "uncertaintyMinus":0.0020378878890699999,
          "uncertaintyPlus":0.0020378878890699999
        },
        {
          "efficiency":0.84307942048700002,
          "pt":41.0,
          "uncertaintyMinus":0.0022864956097400002,
          "uncertaintyPlus":0.0022864956097400002
        },
        {
          "efficiency":0.83543106593700001,
          "pt":45.0,
          "uncertaintyMinus":0.0024743837258399998,
          "uncertaintyPlus":0.0024743837258399998
        },
        {
          "efficiency":0.83505321951699996,
          "pt":50.0,
          "uncertaintyMinus":0.00292746885214,
          "uncertaintyPlus":0.00292746885214
        },
        {
          "efficiency":0.82430701343299995,
          "pt":55.0,
          "uncertaintyMinus":0.0035715454239800002,
          "uncertaintyPlus":0.0035715454239800002
        },
        {
          "efficiency":0.84137920696599999,
          "pt":60.0,
          "uncertaintyMinus":0.0029779644464299998,
          "uncertaintyPlus":0.0029779644464299998
        },
        {
          "efficiency":0.84696894892899999,
          "pt":70.0,
          "uncertaintyMinus":0.0037322820590000002,
          "uncertaintyPlus":0.0037322820590000002
        },
        {
          "efficiency":0.82036472403500005,
          "pt":80.0,
          "uncertaintyMinus":0.0039367618839299999,
          "uncertaintyPlus":0.0039367618839299999
        },
        {
          "efficiency":0.79054373440400005,
          "pt":100.0,
          "uncertaintyMinus":0.0050594940134699997,
          "uncertaintyPlus":0.0050594940134699997
        }
      ]
    },
    "Summer12_PU_Unweighted":{
      "bins":[
        {
          "efficiency":0.056562987870799997,
          "pt":20.0,
          "uncertaintyMinus":0.00146362682516,
          "uncertaintyPlus":0.00149961435574
        },
        {
          "efficiency":0.054272849204800001,
          "pt":25.0,
          "uncertaintyMinus":0.0015703486079699999,
          "uncertaintyPlus":0.0016137023897300001
        },
        {
          "efficiency":0.117187118213,
          "pt":29.0,
          "uncertaintyMinus":0.0022540027468000001,
          "uncertaintyPlus":0.0022918234901300001
        },
        {
          "efficiency":0.55170543896799995,
          "pt":33.0,
          "uncertaintyMinus":0.0036920470092400002,
          "uncertaintyPlus":0.0036863980161800001
        },
        {
          "efficiency":0.81531561684200005,
          "pt":37.0,
          "uncertaintyMinus":0.0032295423575699998,
          "uncertaintyPlus":0.0031868852064800002
        },
        {
          "efficiency":0.82859463850500004,
          "pt":41.0,
          "uncertaintyMinus":0.0036554899706900002,
          "uncertaintyPlus":0.0035954268743000001
        },
        {
          "efficiency":0.83273251622199995,
          "pt":45.0,
          "uncertaintyMinus":0.0038737984974499999,
          "uncertaintyPlus":0.0038043295782299999
        },
        {
          "efficiency":0.82420254613099997,
          "pt":50.0,
          "uncertaintyMinus":0.00467097938766,
          "uncertaintyPlus":0.00457678144136
        },
        {
          "efficiency":0.80671612651299995,
          "pt":55.0,
          "uncertaintyMinus":0.0056756613882800004,
          "uncertaintyPlus":0.0055537920015099997
        },
        {
          "efficiency":0.83004067402699999,
          "pt":60.0,
          "uncertaintyMinus":0.0046480792392699999,
          "uncertaintyPlus":0.0045506625169499998
        },
        {
          "efficiency":0.84097633136100003,
          "pt":70.0,
          "uncertaintyMinus":0.0059509458154699997,
          "uncertaintyPlus":0.0057792260008199996
        },
        {
          "efficiency":0.79728118292399996,
          "pt":80.0,
          "uncertaintyMinus":0.0063995507207599998,
          "uncertaintyPlus":0.0062550484926200004
        },
        {
          "efficiency":0.79301919720799996,
          "pt":100.0,
          "uncertaintyMinus":0.0078473158950399993,
          "uncertaintyPlus":0.00763809149457
        }
      ]
    }
  }
}