{
  "_timestamp":   "Generated on Wed Jul 18 13:26:25 2018 by HiggsAnalysis/NtupleAnalysis/src/TopTaggerEfficiency/work/plot_EfficiencySystTop.py",
  "_rootVersion": "6.05/03",
   "TT_mtop1665" : {
         "bins" : [
               {
                 "pt"              :0.0,
                 "uncertainty"     :-0.0187366802092
                },
               {
                 "pt"              :100.0,
                 "uncertainty"     :-0.00715761266573
                },
               {
                 "pt"              :200.0,
                 "uncertainty"     :-0.000425472592423
                },
               {
                 "pt"              :300.0,
                 "uncertainty"     :-0.000410533092567
                },
               {
                 "pt"              :400.0,
                 "uncertainty"     :-0.00197057956009
                },
               {
                 "pt"              :500.0,
                 "uncertainty"     :0.00669034573612
                }
          ]
      },
   "TT_mtop1695" : {
         "bins" : [
               {
                 "pt"              :0.0,
                 "uncertainty"     :-0.0125341053393
                },
               {
                 "pt"              :100.0,
                 "uncertainty"     :-0.00216243062945
                },
               {
                 "pt"              :200.0,
                 "uncertainty"     :-0.00188227942992
                },
               {
                 "pt"              :300.0,
                 "uncertainty"     :-0.00151881767817
                },
               {
                 "pt"              :400.0,
                 "uncertainty"     :-0.00107302804931
                },
               {
                 "pt"              :500.0,
                 "uncertainty"     :0.006281060616
                }
          ]
      },
   "TT_mtop1715" : {
         "bins" : [
               {
                 "pt"              :0.0,
                 "uncertainty"     :-0.00143010953869
                },
               {
                 "pt"              :100.0,
                 "uncertainty"     :-0.0038872891483
                },
               {
                 "pt"              :200.0,
                 "uncertainty"     :-0.00100634551313
                },
               {
                 "pt"              :300.0,
                 "uncertainty"     :-0.00264530476329
                },
               {
                 "pt"              :400.0,
                 "uncertainty"     :-0.0024110901361
                },
               {
                 "pt"              :500.0,
                 "uncertainty"     :-0.00894753195859
                }
          ]
      },
   "TT_mtop1735" : {
         "bins" : [
               {
                 "pt"              :0.0,
                 "uncertainty"     :-0.0182224872196
                },
               {
                 "pt"              :100.0,
                 "uncertainty"     :-0.00293074451271
                },
               {
                 "pt"              :200.0,
                 "uncertainty"     :-0.00235130158622
                },
               {
                 "pt"              :300.0,
                 "uncertainty"     :-0.00158486101674
                },
               {
                 "pt"              :400.0,
                 "uncertainty"     :-0.0027112893249
                },
               {
                 "pt"              :500.0,
                 "uncertainty"     :-0.0120206583205
                }
          ]
      },
   "TT_mtop1755" : {
         "bins" : [
               {
                 "pt"              :0.0,
                 "uncertainty"     :-0.0134774568655
                },
               {
                 "pt"              :100.0,
                 "uncertainty"     :-0.00546458857219
                },
               {
                 "pt"              :200.0,
                 "uncertainty"     :-0.000871657123981
                },
               {
                 "pt"              :300.0,
                 "uncertainty"     :-0.00250712127616
                },
               {
                 "pt"              :400.0,
                 "uncertainty"     :-0.00300530215601
                },
               {
                 "pt"              :500.0,
                 "uncertainty"     :-0.0044490374157
                }
          ]
      },
   "TT_mtop1785" : {
         "bins" : [
               {
                 "pt"              :0.0,
                 "uncertainty"     :-0.0252281734473
                },
               {
                 "pt"              :100.0,
                 "uncertainty"     :-0.0109164524958
                },
               {
                 "pt"              :200.0,
                 "uncertainty"     :-0.00254049939932
                },
               {
                 "pt"              :300.0,
                 "uncertainty"     :-0.00256541230815
                },
               {
                 "pt"              :400.0,
                 "uncertainty"     :-0.00817365164984
                },
               {
                 "pt"              :500.0,
                 "uncertainty"     :-5.22544245263e-06
                }
          ]
      },
   "TT_fsrdown" : {
         "bins" : [
               {
                 "pt"              :0.0,
                 "uncertainty"     :-0.00564156471296
                },
               {
                 "pt"              :100.0,
                 "uncertainty"     :0.00103077448987
                },
               {
                 "pt"              :200.0,
                 "uncertainty"     :0.00148150321278
                },
               {
                 "pt"              :300.0,
                 "uncertainty"     :0.00149788585807
                },
               {
                 "pt"              :400.0,
                 "uncertainty"     :0.00202489509959
                },
               {
                 "pt"              :500.0,
                 "uncertainty"     :0.0030752591106
                }
          ]
      },
   "TT_fsrup" : {
         "bins" : [
               {
                 "pt"              :0.0,
                 "uncertainty"     :-0.0172531982213
                },
               {
                 "pt"              :100.0,
                 "uncertainty"     :-0.00925750091268
                },
               {
                 "pt"              :200.0,
                 "uncertainty"     :-0.00360701487461
                },
               {
                 "pt"              :300.0,
                 "uncertainty"     :-0.00292419399443
                },
               {
                 "pt"              :400.0,
                 "uncertainty"     :-0.00241813128038
                },
               {
                 "pt"              :500.0,
                 "uncertainty"     :-0.00407568994226
                }
          ]
      },
   "TT_isrdown" : {
         "bins" : [
               {
                 "pt"              :0.0,
                 "uncertainty"     :-0.0075532825956
                },
               {
                 "pt"              :100.0,
                 "uncertainty"     :-0.00176938804657
                },
               {
                 "pt"              :200.0,
                 "uncertainty"     :-0.000475286774985
                },
               {
                 "pt"              :300.0,
                 "uncertainty"     :-0.000839221771878
                },
               {
                 "pt"              :400.0,
                 "uncertainty"     :-0.000398750325406
                },
               {
                 "pt"              :500.0,
                 "uncertainty"     :0.00121773099647
                }
          ]
      },
   "TT_isrup" : {
         "bins" : [
               {
                 "pt"              :0.0,
                 "uncertainty"     :-0.00727393255477
                },
               {
                 "pt"              :100.0,
                 "uncertainty"     :-0.00218006225006
                },
               {
                 "pt"              :200.0,
                 "uncertainty"     :-0.000793593548754
                },
               {
                 "pt"              :300.0,
                 "uncertainty"     :-0.00121636759654
                },
               {
                 "pt"              :400.0,
                 "uncertainty"     :-0.000535162209214
                },
               {
                 "pt"              :500.0,
                 "uncertainty"     :-0.0043141308173
                }
          ]
      }, 
   "TT_hdampDOWN" : {
         "bins" : [
               {
                 "pt"              :0.0,
                 "uncertainty"     :-0.0114985656831
                },
               {
                 "pt"              :100.0,
                 "uncertainty"     :-0.000563182375183
                },
               {
                 "pt"              :200.0,
                 "uncertainty"     :0.000498011477096
                },
               {
                 "pt"              :300.0,
                 "uncertainty"     :-0.000966034138722
                },
               {
                 "pt"              :400.0,
                 "uncertainty"     :0.00065438606109
                },
               {
                 "pt"              :500.0,
                 "uncertainty"     :0.00396443664392
                }
          ]
      },
   "TT_hdampUP" : {
         "bins" : [
               {
                 "pt"              :0.0,
                 "uncertainty"     :-0.00264232078655
                },
               {
                 "pt"              :100.0,
                 "uncertainty"     :-0.000833332362911
                },
               {
                 "pt"              :200.0,
                 "uncertainty"     :0.00056718018823
                },
               {
                 "pt"              :300.0,
                 "uncertainty"     :-0.000145979468808
                },
               {
                 "pt"              :400.0,
                 "uncertainty"     :-0.00574610009459
                },
               {
                 "pt"              :500.0,
                 "uncertainty"     :0.00587623818073
                }
          ]
      }, 
   "TT_TuneEE5C" : {
         "bins" : [
               {
                 "pt"              :0.0,
                 "uncertainty"     :-0.0406296405758
                },
               {
                 "pt"              :100.0,
                 "uncertainty"     :-0.0120662959442
                },
               {
                 "pt"              :200.0,
                 "uncertainty"     :-0.0133383463922
                },
               {
                 "pt"              :300.0,
                 "uncertainty"     :-0.0196191614581
                },
               {
                 "pt"              :400.0,
                 "uncertainty"     :-0.00829689918703
                },
               {
                 "pt"              :500.0,
                 "uncertainty"     :-0.000765518118226
                }
          ]
      }, 
   "TT_evtgen" : {
         "bins" : [
               {
                 "pt"              :0.0,
                 "uncertainty"     :-0.00726134668395
                },
               {
                 "pt"              :100.0,
                 "uncertainty"     :-0.00101341090109
                },
               {
                 "pt"              :200.0,
                 "uncertainty"     :0.000268517320392
                },
               {
                 "pt"              :300.0,
                 "uncertainty"     :0.000119353310328
                },
               {
                 "pt"              :400.0,
                 "uncertainty"     :-0.000313133950965
                },
               {
                 "pt"              :500.0,
                 "uncertainty"     :-0.0198040700992
                }
          ]
      }, 
   "matching" : {
         "bins" : [
               {
                 "pt"              :0.0,
                 "uncertainty"     :0.0114140395904
                },
               {
                 "pt"              :100.0,
                 "uncertainty"     :0.00803731716404
                },
               {
                 "pt"              :200.0,
                 "uncertainty"     :0.00807929309534
                },
               {
                 "pt"              :300.0,
                 "uncertainty"     :0.00768702971567
                },
               {
                 "pt"              :400.0,
                 "uncertainty"     :0.0109338909879
                },
               {
                 "pt"              :500.0,
                 "uncertainty"     :0.0185268070384
                }
          ]
      } 
}